cvrptw_optimization/__init__.py
cvrptw_optimization/single_depot_column_generation_pulp.py
cvrptw_optimization/single_depot_general_model_pulp.py
cvrptw_optimization/data/__init__.py
cvrptw_optimization/data/customers0.pkl
cvrptw_optimization/data/customers1.pkl
cvrptw_optimization/data/customers_unit_test.pkl
cvrptw_optimization/data/data.py
cvrptw_optimization/data/depots0.pkl
cvrptw_optimization/data/depots1.pkl
cvrptw_optimization/data/depots_unit_test.pkl
cvrptw_optimization/data/transportation_matrix0.pkl
cvrptw_optimization/data/transportation_matrix1.pkl
cvrptw_optimization/data/transportation_matrix_unit_test.pkl
cvrptw_optimization/data/vehicles0.pkl
cvrptw_optimization/data/vehicles1.pkl
cvrptw_optimization/data/vehicles_unit_test.pkl
cvrptw_optimization/src/__init__.py
cvrptw_optimization/src/single_depot_column_generation_pulp_inputs.py
cvrptw_optimization/src/single_depot_column_generation_pulp_problem_formulation.py
cvrptw_optimization/src/single_depot_general_model_pulp_formulation.py
cvrptw_optimization/src/single_depot_general_model_pulp_inputs.py
cimren_cvrptw_optimization-1.2.0.dist-info/LICENSE
cimren_cvrptw_optimization-1.2.0.dist-info/METADATA
cimren_cvrptw_optimization-1.2.0.dist-info/WHEEL
cimren_cvrptw_optimization-1.2.0.dist-info/top_level.txt
cimren_cvrptw_optimization-1.2.0.dist-info/RECORD
