Metadata-Version: 2.1
Name: cimren-cvrptw-optimization
Version: 1.2.0
Summary: CVRPTW Optimization Models
Home-page: https://github.com/emrahcimren/cvrptw-optimization
Author: cimren
Author-email: cimren.1@gmail.com
License: MIT
Platform: UNKNOWN
Classifier: License :: OSI Approved :: MIT License
Classifier: Programming Language :: Python :: 3
Classifier: Programming Language :: Python :: 3.6
Requires-Dist: setuptools
Requires-Dist: Pathlib
Requires-Dist: numpy
Requires-Dist: pulp
Requires-Dist: pandas
Requires-Dist: certifi (==2019.11.28)
Requires-Dist: PuLP
Requires-Dist: pyparsing (==2.4.6)
Requires-Dist: python-dateutil (==2.8.1)
Requires-Dist: pytz (==2019.3)
Requires-Dist: six (==1.14.0)
Requires-Dist: wincertstore (==0.2)
